looker_sdk/__init__.py
looker_sdk/error.py
looker_sdk/py.typed
looker_sdk/version.py
looker_sdk/rtl/__init__.py
looker_sdk/rtl/api_methods.py
looker_sdk/rtl/api_settings.py
looker_sdk/rtl/auth_session.py
looker_sdk/rtl/auth_token.py
looker_sdk/rtl/constants.py
looker_sdk/rtl/hooks.py
looker_sdk/rtl/model.py
looker_sdk/rtl/requests_transport.py
looker_sdk/rtl/serialize.py
looker_sdk/rtl/transport.py
looker_sdk/sdk/__init__.py
looker_sdk/sdk/constants.py
looker_sdk/sdk/api40/__init__.py
looker_sdk/sdk/api40/methods.py
looker_sdk/sdk/api40/models.py
tests/integration/__init__.py
tests/integration/test_methods.py
tests/integration/test_netrc.py
tests/rtl/__init__.py
tests/rtl/test_api_methods.py
tests/rtl/test_api_settings.py
tests/rtl/test_auth_session.py
tests/rtl/test_auth_token.py
tests/rtl/test_requests_transport.py
tests/rtl/test_serialize.py
tests/rtl/test_transport.py
looker_sdk-25.16.0.dist-info/LICENSE.txt
looker_sdk-25.16.0.dist-info/METADATA
looker_sdk-25.16.0.dist-info/WHEEL
looker_sdk-25.16.0.dist-info/top_level.txt
looker_sdk-25.16.0.dist-info/RECORD
