Metadata-Version: 2.1
Name: looker-sdk
Version: 25.16.0
Summary: Looker REST API
Home-page: https://pypi.python.org/pypi/looker_sdk
Author: Looker Data Sciences, Inc.
License: MIT
Keywords: Looker,Looker API,looker_sdk,Looker API 4.0
Requires-Python: >=3.6
License-File: LICENSE.txt
